[
  {
    "Name": "Agumon Soul",
    "Id": 694000
  },
  {
    "Name": "Betamon Soul",
    "Id": 694001
  },
  {
    "Name": "Greymon Soul",
    "Id": 694002
  },
  {
    "Name": "Devimon Soul",
    "Id": 694003
  },
  {
    "Name": "Airdramon Soul",
    "Id": 694004
  },
  {
    "Name": "Tyrannomon Soul",
    "Id": 694005
  },
  {
    "Name": "Meramon Soul",
    "Id": 694006
  },
  {
    "Name": "Seadramon Soul",
    "Id": 694007
  },
  {
    "Name": "Numemon Soul",
    "Id": 694008
  },
  {
    "Name": "MetalGreymon Soul",
    "Id": 694009
  },
  {
    "Name": "Mamemon Soul",
    "Id": 694010
  },
  {
    "Name": "Monzaemon Soul",
    "Id": 694011
  },
  {
    "Name": "Gabumon Soul",
    "Id": 694012
  },
  {
    "Name": "Elecmon Soul",
    "Id": 694013
  },
  {
    "Name": "Kabuterimon Soul",
    "Id": 694014
  },
  {
    "Name": "Angemon Soul",
    "Id": 694015
  },
  {
    "Name": "Birdramon Soul",
    "Id": 694016
  },
  {
    "Name": "Garurumon Soul",
    "Id": 694017
  },
  {
    "Name": "Frigimon Soul",
    "Id": 694018
  },
  {
    "Name": "Whamon Soul",
    "Id": 694019
  },
  {
    "Name": "Vegiemon Soul",
    "Id": 694020
  },
  {
    "Name": "SkullGreymon Soul",
    "Id": 694021
  },
  {
    "Name": "MetalMamemon Soul",
    "Id": 694022
  },
  {
    "Name": "Vademon Soul",
    "Id": 694023
  },
  {
    "Name": "Patamon Soul",
    "Id": 694024
  },
  {
    "Name": "Kunemon Soul",
    "Id": 694025
  },
  {
    "Name": "Unimon Soul",
    "Id": 694026
  },
  {
    "Name": "Ogremon Soul",
    "Id": 694027
  },
  {
    "Name": "Shellmon Soul",
    "Id": 694028
  },
  {
    "Name": "Centarumon Soul",
    "Id": 694029
  },
  {
    "Name": "Bakemon Soul",
    "Id": 694030
  },
  {
    "Name": "Drimogemon Soul",
    "Id": 694031
  },
  {
    "Name": "Sukamon Soul",
    "Id": 694032
  },
  {
    "Name": "Andromon Soul",
    "Id": 694033
  },
  {
    "Name": "Giromon Soul",
    "Id": 694034
  },
  {
    "Name": "Etemon Soul",
    "Id": 694035
  },
  {
    "Name": "Biyomon Soul",
    "Id": 694036
  },
  {
    "Name": "Palmon Soul",
    "Id": 694037
  },
  {
    "Name": "Monochromon Soul",
    "Id": 694038
  },
  {
    "Name": "Leomon Soul",
    "Id": 694039
  },
  {
    "Name": "Coelamon Soul",
    "Id": 694040
  },
  {
    "Name": "Kokatorimon Soul",
    "Id": 694041
  },
  {
    "Name": "Kuwagamon Soul",
    "Id": 694042
  },
  {
    "Name": "Mojyamon Soul",
    "Id": 694043
  },
  {
    "Name": "Nanimon Soul",
    "Id": 694044
  },
  {
    "Name": "Megadramon Soul",
    "Id": 694045
  },
  {
    "Name": "Piximon Soul",
    "Id": 694046
  },
  {
    "Name": "Digitamamon Soul",
    "Id": 694047
  },
  {
    "Name": "Penguinmon Soul",
    "Id": 694048
  },
  {
    "Name": "Ninjamon Soul",
    "Id": 694049
  }
]